[{"State":"Brasil","Min":"360.9","Perc25":"508.35","Median":"599.7","Mean":"595.724964767465","Perc75":"678.2","Max":"985","Zeros":"0.000201288244766506"},{"State":"AC","Region":"N","Min":"392.1","Perc25":"463.85","Median":"540.7","Mean":"548.362962962963","Perc75":"621.75","Max":"721.1","Zeros":"0"},{"State":"AL","Region":"NE","Min":"411.5","Perc25":"536.4","Median":"638.95","Mean":"618.790909090909","Perc75":"691.125","Max":"783.5","Zeros":"0"},{"State":"AM","Region":"N","Min":"370","Perc25":"499.75","Median":"568.7","Mean":"572.5","Perc75":"625.475","Max":"820.7","Zeros":"0"},{"State":"AP","Region":"N","Min":"366","Perc25":"434.6","Median":"466.4","Mean":"497.142105263158","Perc75":"565.45","Max":"664.1","Zeros":"0"},{"State":"BA","Region":"NE","Min":"390.6","Perc25":"496.15","Median":"611.8","Mean":"604.286046511628","Perc75":"715.825","Max":"888.9","Zeros":"0"},{"State":"CE","Region":"NE","Min":"362.7","Perc25":"521.1","Median":"627.2","Mean":"599.162264150943","Perc75":"686.5","Max":"846.3","Zeros":"0"},{"State":"DF","Region":"CO","Min":"365.3","Perc25":"490.75","Median":"564.65","Mean":"570.792410714286","Perc75":"643.3","Max":"867.2","Zeros":"0"},{"State":"ES","Region":"SE","Min":"396.5","Perc25":"551.2","Median":"661","Mean":"648.188571428571","Perc75":"732","Max":"898.4","Zeros":"0.00943396226415094"},{"State":"GO","Region":"CO","Min":"360.9","Perc25":"491.025","Median":"576.45","Mean":"575.396666666667","Perc75":"663","Max":"852.5","Zeros":"0"},{"State":"MA","Region":"NE","Min":"369","Perc25":"478.65","Median":"562.7","Mean":"551.171153846154","Perc75":"618.05","Max":"821.6","Zeros":"0"},{"State":"MG","Region":"SE","Min":"361.6","Perc25":"544.95","Median":"626.1","Mean":"622.514331210191","Perc75":"703.9","Max":"985","Zeros":"0"},{"State":"MS","Region":"CO","Min":"371.5","Perc25":"485.4","Median":"571.5","Mean":"574.800869565217","Perc75":"661.75","Max":"819.4","Zeros":"0"},{"State":"MT","Region":"CO","Min":"370.5","Perc25":"479.9","Median":"548.6","Mean":"562.56524822695","Perc75":"649.8","Max":"809.6","Zeros":"0"},{"State":"PA","Region":"N","Min":"369.1","Perc25":"452.2","Median":"538.3","Mean":"541.473195876289","Perc75":"637.3","Max":"765.4","Zeros":"0"},{"State":"PB","Region":"NE","Min":"449.1","Perc25":"530.275","Median":"624.05","Mean":"603.171428571429","Perc75":"679.4","Max":"763.9","Zeros":"0"},{"State":"PE","Region":"NE","Min":"366.4","Perc25":"550.675","Median":"639.55","Mean":"623.521","Perc75":"703.325","Max":"963","Zeros":"0"},{"State":"PI","Region":"NE","Min":"422.4","Perc25":"497.825","Median":"558.65","Mean":"592.161111111111","Perc75":"664.575","Max":"854.4","Zeros":"0"},{"State":"PR","Region":"S","Min":"363.2","Perc25":"511.4","Median":"605.6","Mean":"596.57125","Perc75":"670.175","Max":"939.6","Zeros":"0"},{"State":"RJ","Region":"SE","Min":"363.8","Perc25":"513.5","Median":"616.15","Mean":"606.362021857924","Perc75":"690.95","Max":"942.7","Zeros":"0"},{"State":"RN","Region":"NE","Min":"410","Perc25":"535.75","Median":"627.5","Mean":"619.591304347826","Perc75":"699.775","Max":"845.7","Zeros":"0"},{"State":"RO","Region":"N","Min":"386.3","Perc25":"505.125","Median":"571.05","Mean":"578.65","Perc75":"666.225","Max":"784.8","Zeros":"0"},{"State":"RR","Region":"N","Min":"370.3","Perc25":"475","Median":"551.3","Mean":"562.3","Perc75":"687.8","Max":"796.4","Zeros":"0"},{"State":"RS","Region":"S","Min":"369.8","Perc25":"535.7","Median":"612","Mean":"605.347921225383","Perc75":"681.5","Max":"892.2","Zeros":"0"},{"State":"SC","Region":"S","Min":"365.8","Perc25":"511.65","Median":"598.9","Mean":"594.300895522388","Perc75":"678.15","Max":"918.6","Zeros":"0"},{"State":"SE","Region":"NE","Min":"432.5","Perc25":"541.1","Median":"606.5","Mean":"599.154545454545","Perc75":"654.85","Max":"748.7","Zeros":"0"},{"State":"SP","Region":"SE","Min":"372.4","Perc25":"508.3","Median":"597","Mean":"591.708688906129","Perc75":"669.7","Max":"932.6","Zeros":"0"},{"State":"TO","Region":"N","Min":"361.3","Perc25":"476.7","Median":"555.4","Mean":"572.322580645161","Perc75":"685.15","Max":"762.5","Zeros":"0"}]
