[{"State":"Brasil","Min":"360.7","Perc25":"546.7","Median":"639.8","Mean":"631.458773252891","Perc75":"720.1","Max":"966.4","Zeros":"0"},{"State":"AC","Region":"N","Min":"380.4","Perc25":"426.65","Median":"472.45","Mean":"494.3125","Perc75":"531.225","Max":"716.9","Zeros":"0"},{"State":"AL","Region":"NE","Min":"704.9","Perc25":"726.85","Median":"748.8","Mean":"748.8","Perc75":"770.75","Max":"792.7","Zeros":"0"},{"State":"AM","Region":"N","Min":"404.3","Perc25":"483.175","Median":"578","Mean":"585.5675","Perc75":"665.975","Max":"872","Zeros":"0"},{"State":"AP","Region":"N","Min":"414.2","Perc25":"427.325","Median":"440.45","Mean":"440.45","Perc75":"453.575","Max":"466.7","Zeros":"0"},{"State":"BA","Region":"NE","Min":"366.8","Perc25":"494.45","Median":"572.15","Mean":"594.419047619048","Perc75":"711.55","Max":"871.7","Zeros":"0"},{"State":"CE","Region":"NE","Min":"378.2","Perc25":"586.7","Median":"660.95","Mean":"666.633333333333","Perc75":"761.05","Max":"923.4","Zeros":"0"},{"State":"DF","Region":"CO","Min":"409.6","Perc25":"544.6","Median":"633.9","Mean":"626.540136054422","Perc75":"704.2","Max":"883.5","Zeros":"0"},{"State":"ES","Region":"SE","Min":"376.7","Perc25":"546.35","Median":"701.75","Mean":"663.392647058824","Perc75":"773.125","Max":"966.4","Zeros":"0"},{"State":"GO","Region":"CO","Min":"400.7","Perc25":"561.475","Median":"610.8","Mean":"607.065","Perc75":"652.25","Max":"776.9","Zeros":"0"},{"State":"MA","Region":"NE","Min":"388.5","Perc25":"434.9","Median":"496.65","Mean":"543.45","Perc75":"643.125","Max":"781","Zeros":"0"},{"State":"MG","Region":"SE","Min":"361.7","Perc25":"580.6","Median":"661.8","Mean":"654.996624472574","Perc75":"744.4","Max":"918","Zeros":"0"},{"State":"MS","Region":"CO","Min":"382.2","Perc25":"559.9","Median":"653.7","Mean":"634.651428571429","Perc75":"717.1","Max":"854.2","Zeros":"0"},{"State":"MT","Region":"CO","Min":"387.8","Perc25":"504.05","Median":"586.2","Mean":"591.892727272727","Perc75":"662.4","Max":"803.6","Zeros":"0"},{"State":"PA","Region":"N","Min":"369.1","Perc25":"435.5","Median":"633.4","Mean":"588.979310344828","Perc75":"680.2","Max":"842.6","Zeros":"0"},{"State":"PB","Region":"NE","Min":"396.5","Perc25":"521.225","Median":"606.6","Mean":"606.357142857143","Perc75":"735.85","Max":"786.2","Zeros":"0"},{"State":"PE","Region":"NE","Min":"379.1","Perc25":"537.4","Median":"680.2","Mean":"645.502564102564","Perc75":"744.65","Max":"870.6","Zeros":"0"},{"State":"PI","Region":"NE","Min":"533.5","Perc25":"597.425","Median":"661.35","Mean":"661.35","Perc75":"725.275","Max":"789.2","Zeros":"0"},{"State":"PR","Region":"S","Min":"369.3","Perc25":"534","Median":"641.3","Mean":"625.992715231788","Perc75":"700.35","Max":"904.9","Zeros":"0"},{"State":"RJ","Region":"SE","Min":"361.4","Perc25":"595.475","Median":"692","Mean":"671.154210526316","Perc75":"758.85","Max":"877.6","Zeros":"0"},{"State":"RN","Region":"NE","Min":"492.1","Perc25":"717.9","Median":"735.3","Mean":"742.015384615385","Perc75":"802.4","Max":"918","Zeros":"0"},{"State":"RO","Region":"N","Min":"367.6","Perc25":"516.975","Median":"563.85","Mean":"561.84375","Perc75":"611.25","Max":"709.9","Zeros":"0"},{"State":"RR","Region":"N","Min":"386.5","Perc25":"565.7","Median":"587.8","Mean":"588.807692307692","Perc75":"626.3","Max":"733.7","Zeros":"0"},{"State":"RS","Region":"S","Min":"374.8","Perc25":"559.6","Median":"654.7","Mean":"646.326900584795","Perc75":"730.2","Max":"935.3","Zeros":"0"},{"State":"SC","Region":"S","Min":"406","Perc25":"548.35","Median":"617.95","Mean":"622.4359375","Perc75":"694","Max":"953.7","Zeros":"0"},{"State":"SE","Region":"NE","Min":"360.7","Perc25":"454.825","Median":"551","Mean":"520.425","Perc75":"616.6","Max":"619","Zeros":"0"},{"State":"SP","Region":"SE","Min":"362","Perc25":"538.65","Median":"636.7","Mean":"624.046119733925","Perc75":"708.65","Max":"896","Zeros":"0"},{"State":"TO","Region":"N","Min":"396.3","Perc25":"470.975","Median":"560.8","Mean":"565.713333333333","Perc75":"656.125","Max":"796.9","Zeros":"0"}]
