[{"State":"Brasil","Min":"0","Perc25":"485.7","Median":"527","Mean":"522.32316161276","Perc75":"565.7","Max":"801.7"},{"State":"AC","Region":"N","Min":"40","Perc25":"460","Median":"560","Mean":"552.028886354998","Perc75":"620","Max":"980"},{"State":"AL","Region":"NE","Min":"40","Perc25":"480","Median":"580","Mean":"582.053546140646","Perc75":"660","Max":"1000"},{"State":"AM","Region":"N","Min":"40","Perc25":"460","Median":"540","Mean":"538.965957387121","Perc75":"620","Max":"980"},{"State":"AP","Region":"N","Min":"60","Perc25":"480","Median":"560","Mean":"558.087359600642","Perc75":"620","Max":"980"},{"State":"BA","Region":"NE","Min":"60","Perc25":"480","Median":"580","Mean":"579.889106741707","Perc75":"660","Max":"1000"},{"State":"CE","Region":"NE","Min":"40","Perc25":"500","Median":"600","Mean":"596.323565745911","Perc75":"700","Max":"1000"},{"State":"DF","Region":"CO","Min":"60","Perc25":"520","Median":"600","Mean":"601.090482456836","Perc75":"680","Max":"1000"},{"State":"ES","Region":"SE","Min":"40","Perc25":"520","Median":"600","Mean":"604.317804821332","Perc75":"700","Max":"1000"},{"State":"GO","Region":"CO","Min":"40","Perc25":"480","Median":"580","Mean":"596.688676396578","Perc75":"700","Max":"1000"},{"State":"MA","Region":"NE","Min":"40","Perc25":"480","Median":"560","Mean":"561.73396048396","Perc75":"640","Max":"1000"},{"State":"MG","Region":"SE","Min":"40","Perc25":"520","Median":"600","Mean":"614.105521762939","Perc75":"720","Max":"1000"},{"State":"MS","Region":"CO","Min":"80","Perc25":"480","Median":"560","Mean":"568.635572975856","Perc75":"660","Max":"1000"},{"State":"MT","Region":"CO","Min":"40","Perc25":"460","Median":"560","Mean":"563.814771395076","Perc75":"640","Max":"980"},{"State":"PA","Region":"N","Min":"40","Perc25":"480","Median":"580","Mean":"581.975726969129","Perc75":"660","Max":"1000"},{"State":"PB","Region":"NE","Min":"40","Perc25":"500","Median":"580","Mean":"597.515758325057","Perc75":"680","Max":"1000"},{"State":"PE","Region":"NE","Min":"40","Perc25":"500","Median":"580","Mean":"593.729991804735","Perc75":"680","Max":"1000"},{"State":"PI","Region":"NE","Min":"60","Perc25":"480","Median":"580","Mean":"590.612393376819","Perc75":"680","Max":"1000"},{"State":"PR","Region":"S","Min":"40","Perc25":"500","Median":"580","Mean":"581.63936385571","Perc75":"660","Max":"980"},{"State":"RJ","Region":"SE","Min":"40","Perc25":"520","Median":"600","Mean":"615.226450062922","Perc75":"720","Max":"1000"},{"State":"RN","Region":"NE","Min":"60","Perc25":"520","Median":"580","Mean":"599.869588028081","Perc75":"680","Max":"1000"},{"State":"RO","Region":"N","Min":"80","Perc25":"460","Median":"560","Mean":"551.635803318383","Perc75":"620","Max":"980"},{"State":"RR","Region":"N","Min":"100","Perc25":"460","Median":"560","Mean":"550.012642225032","Perc75":"640","Max":"980"},{"State":"RS","Region":"S","Min":"40","Perc25":"500","Median":"580","Mean":"595.076132607849","Perc75":"680","Max":"1000"},{"State":"SC","Region":"S","Min":"80","Perc25":"520","Median":"600","Mean":"596.616512459724","Perc75":"680","Max":"980"},{"State":"SE","Region":"NE","Min":"80","Perc25":"500","Median":"600","Mean":"608.60971258672","Perc75":"700","Max":"980"},{"State":"SP","Region":"SE","Min":"40","Perc25":"520","Median":"600","Mean":"599.133041954351","Perc75":"680","Max":"1000"},{"State":"TO","Region":"N","Min":"80","Perc25":"480","Median":"560","Mean":"571.490995192653","Perc75":"640","Max":"980"}]
