[{"State":"Brasil","Min":"120","Perc25":"600","Median":"720","Mean":"723.400123304562","Perc75":"860","Max":"1000","Zeros":"0.0101457014265009"},{"State":"AC","Region":"N","Min":"300","Perc25":"600","Median":"700","Mean":"713.833333333333","Perc75":"840","Max":"980","Zeros":"0.00826446280991736"},{"State":"AL","Region":"NE","Min":"320","Perc25":"620","Median":"740","Mean":"738.064516129032","Perc75":"880","Max":"980","Zeros":"0.0274509803921569"},{"State":"AM","Region":"N","Min":"280","Perc25":"580","Median":"660","Mean":"684.830188679245","Perc75":"820","Max":"980","Zeros":"0.022140221402214"},{"State":"AP","Region":"N","Min":"380","Perc25":"580","Median":"660","Mean":"697.888198757764","Perc75":"840","Max":"960","Zeros":"0.0242424242424242"},{"State":"BA","Region":"NE","Min":"240","Perc25":"620","Median":"740","Mean":"731.634241245136","Perc75":"860","Max":"980","Zeros":"0.0105871029836381"},{"State":"CE","Region":"NE","Min":"220","Perc25":"660","Median":"800","Mean":"768.584905660377","Perc75":"900","Max":"980","Zeros":"0.0124223602484472"},{"State":"DF","Region":"CO","Min":"240","Perc25":"580","Median":"680","Mean":"690.555555555556","Perc75":"800","Max":"1000","Zeros":"0.0124688279301746"},{"State":"ES","Region":"SE","Min":"240","Perc25":"600","Median":"760","Mean":"742.538461538462","Perc75":"900","Max":"980","Zeros":"0.0114068441064639"},{"State":"GO","Region":"CO","Min":"240","Perc25":"635","Median":"780","Mean":"749.247572815534","Perc75":"900","Max":"980","Zeros":"0.00483091787439614"},{"State":"MA","Region":"NE","Min":"280","Perc25":"620","Median":"720","Mean":"723.535108958838","Perc75":"860","Max":"1000","Zeros":"0.0259433962264151"},{"State":"MG","Region":"SE","Min":"120","Perc25":"640","Median":"800","Mean":"762.610103626943","Perc75":"900","Max":"980","Zeros":"0.00643500643500643"},{"State":"MS","Region":"CO","Min":"220","Perc25":"620","Median":"740","Mean":"729.78835978836","Perc75":"860","Max":"1000","Zeros":"0.0130548302872063"},{"State":"MT","Region":"CO","Min":"240","Perc25":"580","Median":"700","Mean":"700.11811023622","Perc75":"840","Max":"980","Zeros":"0.0174081237911025"},{"State":"PA","Region":"N","Min":"260","Perc25":"620","Median":"760","Mean":"743.486529318542","Perc75":"880","Max":"980","Zeros":"0.015600624024961"},{"State":"PB","Region":"NE","Min":"340","Perc25":"640","Median":"760","Mean":"752.205128205128","Perc75":"880","Max":"980","Zeros":"0.0126582278481013"},{"State":"PE","Region":"NE","Min":"240","Perc25":"620","Median":"740","Mean":"733.728070175439","Perc75":"860","Max":"980","Zeros":"0.0214592274678112"},{"State":"PI","Region":"NE","Min":"280","Perc25":"680","Median":"820","Mean":"780.514469453376","Perc75":"920","Max":"980","Zeros":"0.00955414012738853"},{"State":"PR","Region":"S","Min":"240","Perc25":"600","Median":"680","Mean":"687.243816254417","Perc75":"800","Max":"980","Zeros":"0.00527240773286467"},{"State":"RJ","Region":"SE","Min":"220","Perc25":"620","Median":"740","Mean":"739.387274155538","Perc75":"880","Max":"980","Zeros":"0.00624512099921936"},{"State":"RN","Region":"NE","Min":"280","Perc25":"620","Median":"740","Mean":"731.604938271605","Perc75":"860","Max":"980","Zeros":"0.0141987829614604"},{"State":"RO","Region":"N","Min":"240","Perc25":"580","Median":"680","Mean":"685.273631840796","Perc75":"800","Max":"980","Zeros":"0.0147058823529412"},{"State":"RR","Region":"N","Min":"260","Perc25":"540","Median":"640","Mean":"642.933333333333","Perc75":"740","Max":"960","Zeros":"0"},{"State":"RS","Region":"S","Min":"220","Perc25":"600","Median":"720","Mean":"707.594575303355","Perc75":"840","Max":"980","Zeros":"0.0112914608327452"},{"State":"SC","Region":"S","Min":"260","Perc25":"600","Median":"680","Mean":"696.646415552855","Perc75":"820","Max":"980","Zeros":"0.0108173076923077"},{"State":"SE","Region":"NE","Min":"260","Perc25":"660","Median":"760","Mean":"757.142857142857","Perc75":"880","Max":"980","Zeros":"0.0160642570281124"},{"State":"SP","Region":"SE","Min":"120","Perc25":"600","Median":"700","Mean":"705.992509363296","Perc75":"820","Max":"980","Zeros":"0.00831971475263705"},{"State":"TO","Region":"N","Min":"240","Perc25":"620","Median":"760","Mean":"734.917127071823","Perc75":"880","Max":"980","Zeros":"0.00549450549450549"}]
